extract_version/__init__.py
extract_version/version.py
extract_version/version_info.py
extract_version-1.1.0.dist-info/LICENSE
extract_version-1.1.0.dist-info/METADATA
extract_version-1.1.0.dist-info/WHEEL
extract_version-1.1.0.dist-info/top_level.txt
extract_version-1.1.0.dist-info/RECORD
