Metadata-Version: 2.1
Name: extract-version
Version: 1.1.0
Summary: Python module for extracting version from the string or directory name
Home-page: https://github.com/yuchdev/ExtractVersion
Download-URL: https://github.com/yuchdev/ExtractVersion/releases/download/release.1.1.0/extract_version-1.1.0.tar.gz
Author: Yurii Cherkasov
Author-email: strategarius@protonmail.com
Project-URL: Bug Tracker, https://github.com/yuchdev/ExtractVersion/issues
Classifier: Development Status :: 4 - Beta
Classifier: Intended Audience :: Developers
Classifier: Programming Language :: Python :: 3
Classifier: License :: OSI Approved :: MIT License
Classifier: Operating System :: OS Independent
Requires-Python: >=3.8
License-File: LICENSE
Requires-Dist: pathlib
